
{
  "tenant_id": "socorro",
  "name": "Gest찾o com Dados - Socorro",
  "logo_url": "/lovable-uploads/socorro_logo.png",
  "primary_color": "#1E90FF",
  "secondary_color": "#FFD700",
  "accent_color": "#32CD32",
  "favicon": "/lovable-uploads/socorro_favicon.png",
  "welcome_message": "Bem-vindo ao Observat처rio de Dados de Socorro",
  "footer_text": "Desenvolvido por Observat처rio de Dados de Socorro",
  "tagline": "Observat처rio Municipal",
  "background_image": "/lovable-uploads/socorro_background.jpg",
  "blur_color": "#1E90FF",
  "blur_opacity": 0.3
}
